jsonrpc_client/__init__.py
bws_jsonrpc_client-0.0.1.dist-info/LICENSE
bws_jsonrpc_client-0.0.1.dist-info/WHEEL
bws_jsonrpc_client-0.0.1.dist-info/METADATA
bws_jsonrpc_client-0.0.1.dist-info/RECORD
