Metadata-Version: 2.1
Name: bws-jsonrpc-client
Version: 0.0.1
Summary: Bws Json RPC Client 
Author: Jose Angel Delgado
Author-email: esojangel@gmail.com
Requires-Python: >=3.6
Classifier: License :: OSI Approved :: Apache Software License
Classifier: Intended Audience :: Developers
Classifier: License :: OSI Approved :: BSD License
Classifier: Programming Language :: Python :: 3.6
Classifier: Programming Language :: Python :: 3.7
Classifier: Programming Language :: Python :: 3.8
Classifier: Programming Language :: Python :: 3.9
Classifier: Topic :: Software Development :: Libraries :: Python Modules
Requires-Dist: requests
